examples/__init__.py
logstyles/__init__.py
logstyles/base_formats.py
logstyles/format_generator.py
logstyles/formatter.py
logstyles/themes.py
logstyles/utils.py
logstyles-0.1.5.dist-info/LICENSE
logstyles-0.1.5.dist-info/METADATA
logstyles-0.1.5.dist-info/WHEEL
logstyles-0.1.5.dist-info/top_level.txt
logstyles-0.1.5.dist-info/RECORD
